discord_simple_pretty_help/__init__.py
discord_simple_pretty_help-0.0.1.dist-info/METADATA
discord_simple_pretty_help-0.0.1.dist-info/WHEEL
discord_simple_pretty_help-0.0.1.dist-info/licenses/LICENSE
discord_simple_pretty_help-0.0.1.dist-info/RECORD
