Metadata-Version: 2.1
Name: discord_simple_pretty_help
Version: 0.0.1
Summary:  A simple yet pretty help menu for discord.py bots 
Project-URL: Homepage, https://github.com/victorbnl/discord-simple-pretty-help
Project-URL: Bug Tracker, https://github.com/victorbnl/discord-simple-pretty-help/issues
Author-email: Victor Bonnelle <victor.bonnelle@proton.me>
License: MIT
Requires-Python: >=3.7
